<?xml version="1.0" encoding="UTF-8"?><xfa:data xmlns:xfa="http://www.xfa.org/schema/xfa-data/1.0/"><form1><Page1><Insturctions xfa:dataNode="dataGroup" /><JoiningFormA><Title>Dr.</Title><FirstName>sdfsadf</FirstName><MiddleName>sdfsafd</MiddleName><LastName>sdfs</LastName><Gender>Female</Gender><MaritalStatus>Divorced</MaritalStatus><DateOfMarraige /><Nationality /><OtherNationality /><BloodGroup /><Religion /><QualificationObtained /><FatherName /><DeceasedCheck>0</DeceasedCheck><FatherDeceasedDate /><QualificationObtained /><SpouseName /><PassportNumber /><PassportValidFrom /><PassportValidTo /><PassportCheck>0</PassportCheck><PANCardNumber /><AdhaarCardNumber /><IndianNational /><IndianNationalYes /><SpeciallyabledCheck /><SpeciallyAbledCategory /></JoiningFormA><JoiningFormB><MobileNumber /><EmailId /><HomeEmergencyNumber /><PermAddress><PermAdressLine1 /><PermAdressLine2 /><PermAdressCity /><PermAdressState /><PermAdressPin /></PermAddress><CurrentPermAddressSameCheck>0</CurrentPermAddressSameCheck><CurrentAddress><CurrentAddressPin /><CurrentAddressState /><CurrentAddressCity /><CurrentAddressLine2 /><CurrentAddressLine1 /></CurrentAddress></JoiningFormB></Page1><Page2><JoiningFormC><SingleDependentsCheck><FatherName /><MotherName /><FatherGender /><MotherGender /></SingleDependentsCheck><MarriedDependentsCheck><Spouse><SpouseName /><SpouseGender /></Spouse><Child><Child1Name /><Child2Name /><Child1Gender /><Child2Gender /></Child><InLaws><FatherInLawName /><MotherInLawName /><MotherInLawGender /><FatheInLawGender /></InLaws></MarriedDependentsCheck><LGBTForm><LGBTGender /><LGBTName /></LGBTForm><DomesticPartner><DPartGender /><DpartName /></DomesticPartner></JoiningFormC><StatutoryFormAText><StatutoryFormAText xfa:dataNode="dataGroup" /></StatutoryFormAText><StatutoryFormANominee><CopyCurrentOrPermAddress>0</CopyCurrentOrPermAddress><PFNomineeName>asdfsdf</PFNomineeName><PFNomineeRelationship /><PFNomineeDOB /><PFPercentageShare /><PFPermAddressLine2 /><PFPermAddressPin /><PFPermAddressState /><PFPermAddressCity /><PFPermAddressLine1>sfdsfdsa</PFPermAddressLine1><PFNomineeGaurdianName /><CopyAddressOptions /></StatutoryFormANominee><StatutoryFormANominee1><CopyCurrentOrPermAddress>0</CopyCurrentOrPermAddress><PFNomineeName /><PFNomineeRelationship /><PFNomineeDOB /><PFPercentageShare /><PFPermAddressLine2 /><PFPermAddressPin /><PFPermAddressState /><PFPermAddressCity /><PFPermAddressLine1 /><PFNomineeGaurdianName /><CopyAddressOptions /></StatutoryFormANominee1><StatutoryFormANominee2><CopyCurrentOrPermAddress>0</CopyCurrentOrPermAddress><PFNomineeName /><PFNomineeRelationship /><PFNomineeDOB /><PFPercentageShare /><PFPermAddressLine2 /><PFPermAddressPin /><PFPermAddressState /><PFPermAddressCity /><PFPermAddressLine1 /><PFNomineeGaurdianName /><CopyAddressOptions /></StatutoryFormANominee2><StatutoryFormANominee3><CopyCurrentOrPermAddress>0</CopyCurrentOrPermAddress><PFNomineeName /><PFNomineeRelationship /><PFNomineeDOB /><PFPercentageShare /><PFPermAddressLine2 /><PFPermAddressPin /><PFPermAddressState /><PFPermAddressCity /><PFPermAddressLine1 /><PFNomineeGaurdianName /><CopyAddressOptions /></StatutoryFormANominee3></Page2><Page3><StatutoryFormCText><StatutoryFormAText xfa:dataNode="dataGroup" /><PFGratuityNominationsSameCheck>0</PFGratuityNominationsSameCheck></StatutoryFormCText><StatutoryFormCNominee><GratuityNomineeDOB /><GratuityNomineeRelationship /><GratuityPercentageShare /><GratuityNomineeName /><GratuityNomineeGaurdianName /><CopyAddressOptions /><GratuityPermAdressCity /><GratuityPermAdressPin /><GratuityPermAdressState /><GratuityPermAdressLine1 /><GratuityPermAdressLine2 /></StatutoryFormCNominee><StatutoryFormCNominee1><GratuityNomineeDOB /><GratuityNomineeRelationship /><GratuityPercentageShare /><GratuityNomineeName /><GratuityNomineeGaurdianName /><CopyAddressOptions /><GratuityPermAdressCity /><GratuityPermAdressPin /><GratuityPermAdressState /><GratuityPermAdressLine1 /><GratuityPermAdressLine2 /></StatutoryFormCNominee1><StatutoryFormCNominee2><GratuityNomineeDOB /><GratuityNomineeRelationship /><GratuityPercentageShare /><GratuityNomineeName /><GratuityNomineeGaurdianName /><CopyAddressOptions /><GratuityPermAdressCity /><GratuityPermAdressPin /><GratuityPermAdressState /><GratuityPermAdressLine1 /><GratuityPermAdressLine2 /></StatutoryFormCNominee2><StatutoryFormCNominee3><GratuityNomineeDOB /><GratuityNomineeRelationship /><GratuityPercentageShare /><GratuityNomineeName /><GratuityNomineeGaurdianName /><CopyAddressOptions /><GratuityPermAdressCity /><GratuityPermAdressPin /><GratuityPermAdressState /><GratuityPermAdressLine1 /><GratuityPermAdressLine2 /></StatutoryFormCNominee3><Form11><PFSchemeEarlierMember /><PensionSchemeEarlierMember /><UAN /><PF /><NameofEmployer /><SchemeCertificateNumber /><PPONumber /><CountryOfOrigin /><IntWorker /><PassDetails><PassportNumber /><PassportValidFrom /><PassportValidTo /></PassDetails></Form11><DeclarationUndetakingText><RadioButtonList /><Name>sdfsadf</Name><Date>2018-10-25</Date><Signature /></DeclarationUndetakingText><JoiningFormD><PSID /><EmployerName>RBS Services India Pvt Ltd</EmployerName><CandidatePartnerName /><BusinessUnit /><Department /><Designation /><CostCentre /><JoinerLocation /><TAMID /><ApplicantID /></JoiningFormD></Page3><Page4><DeclarationUnderatakingQs><D1Q1Yes>0</D1Q1Yes><D1Q1NO>0</D1Q1NO><D1Q2No>0</D1Q2No><D1Q2Yes>0</D1Q2Yes><D1Q3No>0</D1Q3No><D1Q3Yes>0</D1Q3Yes><D1Q4No>0</D1Q4No><D1Q4Yes>0</D1Q4Yes><CurrentPermAddressSameCheck>0</CurrentPermAddressSameCheck><CurrentPermAddressSameCheck>0</CurrentPermAddressSameCheck><CurrentPermAddressSameCheck>0</CurrentPermAddressSameCheck><CurrentPermAddressSameCheck>0</CurrentPermAddressSameCheck><CurrentPermAddressSameCheck>0</CurrentPermAddressSameCheck><CurrentPermAddressSameCheck>0</CurrentPermAddressSameCheck><CurrentPermAddressSameCheck>0</CurrentPermAddressSameCheck><CurrentPermAddressSameCheck>0</CurrentPermAddressSameCheck><CurrentPermAddressSameCheck>0</CurrentPermAddressSameCheck><CurrentPermAddressSameCheck>0</CurrentPermAddressSameCheck><CurrentPermAddressSameCheck>0</CurrentPermAddressSameCheck><CurrentPermAddressSameCheck>0</CurrentPermAddressSameCheck></DeclarationUnderatakingQs></Page4><Page5><DeclarationUndertakingQContd><ContactDetailsText /><CurrentPermAddressSameCheck>0</CurrentPermAddressSameCheck><CurrentPermAddressSameCheck>0</CurrentPermAddressSameCheck><CurrentPermAddressSameCheck>0</CurrentPermAddressSameCheck><CurrentPermAddressSameCheck>0</CurrentPermAddressSameCheck></DeclarationUndertakingQContd><ProofOfActivity><SetUpByDetails><Name><GapStartDate /></Name><ISV><GapEndDate /></ISV><Date><Date /></Date></SetUpByDetails></ProofOfActivity><AuthorisationAndDeclaration><RadioButtonList /><Name>sdfsadf sdfsafd sdfs</Name><DateField1 /></AuthorisationAndDeclaration></Page5><Page6 xfa:dataNode="dataGroup" /><DOB /><FathersDOB /><MotherDOB /><FatherDOB /><SpouseDOB /><Child1DOB /><Child2DOB /><FatherInLawDOB /><MotherInLawDOB /><LGBTDOB /><DpartDOB /><DateOfJoinPrrevEmployement /><DateOfExitPrrevEmployement /><JoiningDate /></form1></xfa:data>